rereplace/__init__.py
rereplace/rereplace.py
rereplace-1.0.0.dist-info/DESCRIPTION.rst
rereplace-1.0.0.dist-info/METADATA
rereplace-1.0.0.dist-info/RECORD
rereplace-1.0.0.dist-info/WHEEL
rereplace-1.0.0.dist-info/metadata.json
rereplace-1.0.0.dist-info/top_level.txt
